spae/__init__.py
spae/aggregation/__init__.py
spae/aggregation/data.py
spae/aggregation/exceptions.py
spae/aggregation/utils.py
spae/aql/__init__.py
spae/aql/compiler.py
spae/aql/components.py
spae/aql/exceptions.py
spae/schema/__init__.py
spae/spark/__init__.py
spae-1.0.0.dist-info/METADATA
spae-1.0.0.dist-info/WHEEL
spae-1.0.0.dist-info/top_level.txt
spae-1.0.0.dist-info/RECORD
