Metadata-Version: 2.1
Name: spae
Version: 1.0.0
Summary: Sparked Parallel Aggregation Concentrated Engine
Home-page: https://github.com/RayYangFromOrderly/spae
Author: RayYang
Author-email: ray.yang@ezorderly.com
License: BSD
Classifier: Development Status :: 5 - Production/Stable
Classifier: Framework :: Django
Classifier: Intended Audience :: Developers
Classifier: License :: OSI Approved :: BSD License
Classifier: Operating System :: OS Independent
Classifier: Programming Language :: Python :: 3.5
Classifier: Topic :: Internet :: WWW/HTTP
Requires-Dist: setuptools
Requires-Dist: requests
Requires-Dist: pyspark
